backupchan_cli/__init__.py
backupchan_cli/main.py
backupchan_cli/progressbar.py
backupchan_cli/utility.py
backupchan_cli/commands/backup.py
backupchan_cli/commands/config.py
backupchan_cli/commands/job.py
backupchan_cli/commands/log.py
backupchan_cli/commands/preset.py
backupchan_cli/commands/recyclebin.py
backupchan_cli/commands/stats.py
backupchan_cli/commands/target.py
backupchan_cli-0.10.0.dist-info/licenses/LICENSE
backupchan_cli-0.10.0.dist-info/METADATA
backupchan_cli-0.10.0.dist-info/WHEEL
backupchan_cli-0.10.0.dist-info/entry_points.txt
backupchan_cli-0.10.0.dist-info/top_level.txt
backupchan_cli-0.10.0.dist-info/RECORD
