Metadata-Version: 2.4
Name: backupchan-cli
Version: 0.10.0
Summary: Command-line interface for interacting with Backup-chan.
Author-email: Moltony <koronavirusnyj@gmail.com>
License: BSD-3-Clause
Project-URL: Homepage, https://github.com/Backupchan/cli
Project-URL: Repository, https://github.com/Backupchan/cli.git
Project-URL: Issues, https://github.com/Backupchan/cli/issues
Project-URL: Changelog, https://github.com/Backupchan/cli/blob/main/CHANGELOG.md
Classifier: Development Status :: 5 - Production/Stable
Classifier: Environment :: Console
Classifier: License :: OSI Approved :: BSD License
Classifier: Natural Language :: English
Classifier: Operating System :: OS Independent
Classifier: Programming Language :: Python :: 3 :: Only
Classifier: Topic :: System :: Archiving :: Backup
Classifier: Typing :: Typed
License-File: LICENSE
Requires-Dist: backupchan-client-lib>=1.4.1
Requires-Dist: backupchan-client-config>=0.1.0
Requires-Dist: backupchan-presets>=0.2.2
Dynamic: license-file
